graphviper/__init__.py
graphviper/graph_tools/__init__.py
graphviper/graph_tools/append.py
graphviper/graph_tools/coordinate_utils.py
graphviper/graph_tools/generate_airflow_workflow.py
graphviper/graph_tools/generate_dask_workflow.py
graphviper/graph_tools/map.py
graphviper/graph_tools/reduce.py
graphviper-0.0.36.dist-info/licenses/LICENSE.txt
graphviper-0.0.36.dist-info/METADATA
graphviper-0.0.36.dist-info/WHEEL
graphviper-0.0.36.dist-info/top_level.txt
graphviper-0.0.36.dist-info/RECORD
