Metadata-Version: 2.4
Name: graphviper
Version: 0.0.36
Summary: Visibility and Image Parallel Execution Reduction for Radio Astronomy 
Author-email: Jan-Willem Steeb <jsteeb@nrao.edu>, Joshua Hoskins <jhoskins@nrao.edu>
License: BSD 3-Clause License
Requires-Python: <3.14,>=3.11
License-File: LICENSE.txt
Requires-Dist: xradio>=1.0.1
Provides-Extra: python-casacore
Requires-Dist: python_casacore>=3.6.1; sys_platform != "darwin" and extra == "python-casacore"
Provides-Extra: test
Requires-Dist: pytest; extra == "test"
Requires-Dist: pytest-cov; extra == "test"
Requires-Dist: pytest-html; extra == "test"
Provides-Extra: interactive
Requires-Dist: bokeh; extra == "interactive"
Requires-Dist: graphviz; extra == "interactive"
Requires-Dist: matplotlib; extra == "interactive"
Requires-Dist: ipywidgets; extra == "interactive"
Requires-Dist: prettytable; extra == "interactive"
Requires-Dist: jupyterlab; extra == "interactive"
Requires-Dist: ipykernel; extra == "interactive"
Requires-Dist: ipympl; extra == "interactive"
Requires-Dist: ipython; extra == "interactive"
Requires-Dist: jupyter-client; extra == "interactive"
Provides-Extra: docs
Requires-Dist: ipykernel; extra == "docs"
Requires-Dist: ipympl; extra == "docs"
Requires-Dist: ipython; extra == "docs"
Requires-Dist: jupyter-client; extra == "docs"
Requires-Dist: nbsphinx; extra == "docs"
Requires-Dist: recommonmark; extra == "docs"
Requires-Dist: scanpydoc; extra == "docs"
Requires-Dist: sphinx-autoapi; extra == "docs"
Requires-Dist: sphinx-autosummary-accessors; extra == "docs"
Requires-Dist: sphinx_rtd_theme; extra == "docs"
Requires-Dist: twine; extra == "docs"
Requires-Dist: pandoc; extra == "docs"
Provides-Extra: all
Requires-Dist: python_casacore>=3.6.1; sys_platform != "darwin" and extra == "all"
Requires-Dist: pytest; extra == "all"
Requires-Dist: pytest-cov; extra == "all"
Requires-Dist: pytest-html; extra == "all"
Requires-Dist: bokeh; extra == "all"
Requires-Dist: graphviz; extra == "all"
Requires-Dist: matplotlib; extra == "all"
Requires-Dist: ipywidgets; extra == "all"
Requires-Dist: prettytable; extra == "all"
Requires-Dist: jupyterlab; extra == "all"
Requires-Dist: ipykernel; extra == "all"
Requires-Dist: ipympl; extra == "all"
Requires-Dist: ipython; extra == "all"
Requires-Dist: jupyter-client; extra == "all"
Requires-Dist: ipykernel; extra == "all"
Requires-Dist: ipympl; extra == "all"
Requires-Dist: ipython; extra == "all"
Requires-Dist: jupyter-client; extra == "all"
Requires-Dist: nbsphinx; extra == "all"
Requires-Dist: recommonmark; extra == "all"
Requires-Dist: scanpydoc; extra == "all"
Requires-Dist: sphinx-autoapi; extra == "all"
Requires-Dist: sphinx-autosummary-accessors; extra == "all"
Requires-Dist: sphinx_rtd_theme; extra == "all"
Requires-Dist: twine; extra == "all"
Requires-Dist: pandoc; extra == "all"
Dynamic: license-file
